bmpr/__init__.py
bmpr/__main__.py
bmpr/cli.py
bmpr-0.0.3.dist-info/AUTHORS.rst
bmpr-0.0.3.dist-info/LICENSE
bmpr-0.0.3.dist-info/METADATA
bmpr-0.0.3.dist-info/WHEEL
bmpr-0.0.3.dist-info/entry_points.txt
bmpr-0.0.3.dist-info/top_level.txt
bmpr-0.0.3.dist-info/RECORD
